odoo/addons/report_qweb_element_page_visibility/README.rst
odoo/addons/report_qweb_element_page_visibility/__init__.py
odoo/addons/report_qweb_element_page_visibility/__manifest__.py
odoo/addons/report_qweb_element_page_visibility/i18n/it.po
odoo/addons/report_qweb_element_page_visibility/i18n/report_qweb_element_page_visibility.pot
odoo/addons/report_qweb_element_page_visibility/readme/CONTRIBUTORS.md
odoo/addons/report_qweb_element_page_visibility/readme/CREDITS.md
odoo/addons/report_qweb_element_page_visibility/readme/DESCRIPTION.md
odoo/addons/report_qweb_element_page_visibility/readme/USAGE.md
odoo/addons/report_qweb_element_page_visibility/static/description/icon.png
odoo/addons/report_qweb_element_page_visibility/static/description/index.html
odoo/addons/report_qweb_element_page_visibility/views/layouts.xml
odoo_addon_report_qweb_element_page_visibility-19.0.1.0.0.2.dist-info/METADATA
odoo_addon_report_qweb_element_page_visibility-19.0.1.0.0.2.dist-info/WHEEL
odoo_addon_report_qweb_element_page_visibility-19.0.1.0.0.2.dist-info/top_level.txt
odoo_addon_report_qweb_element_page_visibility-19.0.1.0.0.2.dist-info/RECORD
