Metadata-Version: 2.1
Name: odoo-addon-report_qweb_element_page_visibility
Version: 19.0.1.0.0.2
Requires-Dist: odoo==19.0.*
Summary: Report Qweb Element Page Visibility
Home-page: https://github.com/OCA/reporting-engine
License: AGPL-3
Author: Agile Business Group, Odoo Community Association (OCA)
Author-email: support@odoo-community.org
Classifier: Programming Language :: Python
Classifier: Framework :: Odoo
Classifier: Framework :: Odoo :: 19.0
Classifier: License :: OSI Approved :: GNU Affero General Public License v3
